204.33.486/RTL/BSP/DecodingProcessControl/wr_update_handshake.v
`timescale 1ns/1ps
module cnu_wr_update_handshake #(
	parameter CDC_DEPTH = 2 // two flip-flops synchroniser for CDC
)(
	output wire cnu_wr_o,
	output wire init_load_o,
	output wire pipe_load_o,

	input wire iter_update_i,
	input wire cnu_rd_finish_i, // whether the 2-input decomposed LUT (F_{0} - F_{dc-2-1}) is finished read operation in the current iteration
	input wire cnu_init_load_en_i, // the FSM is at "initial load" state when assertion is given
	//input wire write_clk,
	input wire read_clk,
	input wire rstn 
);
	wire iter_update;
	reg [CDC_DEPTH-1:0] syncIterUp;
	initial syncIterUp <= 0;
	always @(posedge read_clk, negedge rstn) begin
		if(rstn == 1'b0) syncIterUp[0] <= 1'b0;
		else syncIterUp[0] <= iter_update_i;
	end
	generate
		genvar i;
		for(i=1;i<CDC_DEPTH;i=i+1) begin : cnu_cdc_inst
			always @(posedge read_clk, negedge rstn) begin
				if(rstn == 1'b0) syncIterUp[i] <= 1'b0;
				else syncIterUp[i] <= syncIterUp[i-1];
			end
		end
	endgenerate
	//assign iter_update = syncIterUp[CDC_DEPTH-1];
	assign iter_update = iter_update_i;

	// The inputs source of both "init load" and "cnu pipe" update state
	// signals ought to be latched to synchronise with the timing our
	// init_load_o, pipe_load_o and cnu_wr_o
	reg cnu_rd_finish; //initial cnu_rd_finish <= 1'b0;
	always @(posedge read_clk, negedge rstn) begin
		if(rstn == 1'b0) cnu_rd_finish <= 1'b0;
		else cnu_rd_finish <= cnu_rd_finish_i;
	end
	reg cnu_init_load_en; //initial cnu_init_load_en <= 1'b0;
	always @(posedge read_clk, negedge rstn) begin
		if(rstn == 1'b0) cnu_init_load_en <= 1'b0;
		else cnu_init_load_en <= cnu_init_load_en_i;
	end
	
	wire sig_0, sig_1, sig_2, sig_3, sig_4, sig_5, sig_6, sig_7;
	xnor u0(sig_0, cnu_wr_o, iter_update);
	or   u1(sig_1, init_load_o, pipe_load_o);
	and  u2(sig_2, sig_0, sig_1);
	
	xnor u3(sig_3, sig_2, cnu_wr_o);
	and  u4(sig_4, sig_2, ~cnu_wr_o);
	or   u5(sig_5, sig_3, sig_4);
	and  u6(sig_6, sig_5, cnu_init_load_en_i);
	and  u7(sig_7, sig_5, cnu_rd_finish_i);

	reg cnu_wr_reg; initial cnu_wr_reg <= 0;
	always @(posedge read_clk, negedge rstn) begin
		if(rstn == 1'b0)
			cnu_wr_reg <= 1'b0;
		else
			cnu_wr_reg <= sig_2;
	end
	assign cnu_wr_o = cnu_wr_reg;
	
	reg [1:0] wr_trace; initial wr_trace[1:0] <= 2'd0;
	always @(negedge read_clk, negedge rstn) begin
	   if(rstn == 1'b0) wr_trace[1:0] <= 2'd0;
	   else wr_trace[1:0] <= {wr_trace[0], cnu_wr_o};
	end

	reg init_load_reg; initial init_load_reg <= 0;
	always @(posedge read_clk, negedge rstn) begin
		if(rstn == 1'b0)
			init_load_reg <= 1'b0;
		else begin
            if(wr_trace[1:0] == 2'b10) init_load_reg <= 1'b0;
            else init_load_reg <= sig_6;
		end
	end
	assign init_load_o = init_load_reg;
	
	reg pipe_load_reg; initial pipe_load_reg <= 0;
	always @(posedge read_clk, negedge rstn) begin
		if(rstn == 1'b0)
			pipe_load_reg <= 1'b0;
		else begin
            if(wr_trace[1:0] == 2'b10) pipe_load_reg <= 1'b0;
            else pipe_load_reg <= sig_7;
		end
	end
	assign pipe_load_o = pipe_load_reg;
endmodule

204.33.486/RTL/BSP/DecodingProcessControl/wr_update_handshake_tb.sv
`timescale 1ns/1ps

module cnu_wr_update_handshake_tb;

	initial begin
		$dumpfile("cnu_wr_update.vcd");
		$dumpvars(0, cnu_wr_update_handshake_tb);
	end

	logic read_clk;
 	initial begin
		#0 read_clk <= 1'b0;
		forever #5 read_clk <= ~read_clk;
	end
	logic write_clk;
	initial begin
		#0 write_clk <= 1'b0;
		forever #2 write_clk <= ~write_clk;
	end

	logic rstn;
	initial begin
		#0 rstn <= 1'b0;
		#20 rstn <= 1'b1;
	end

	default clocking cb@(posedge write_clk);
	endclocking

	logic cnu_wr_o, iter_update_i, cnu_rd_finish_i, init_load_o, pipe_load_o;
	reg cnu_init_load_en_i;
	cnu_wr_update_handshake handshake_u0 (.*);
    
	initial begin
		#0  begin
//			cnu_init_load_en_i <= 1'b0;
			cnu_rd_finish_i <= 1'b0;
		end
/*
		#(20+10+5) cnu_init_load_en_i <= 1'b1;
		wait(init_load_o == 1);
		wait(init_load_o == 0);
		cnu_init_load_en_i <= 1'b0;
*/
/*
		#(10*6) cnu_rd_finish_i <= 1'b1;
		wait(pipe_load_o == 1) #10;
		wait(pipe_load_o == 0) #10;
		cnu_rd_finish_i <= 1'b0;
*/
	end

    reg is_init_load; initial is_init_load <= 0;
	reg [9:0] i; initial #0 i <= 0;
	always @(posedge read_clk, negedge rstn) begin
	   if(rstn == 1'b0) i <= 0;
	   else if(i > 2) i <= 0;
	   else if(cnu_init_load_en_i == 1 || cnu_rd_finish_i == 1) i <= i + 1;
	end
	always @(posedge read_clk, negedge rstn) begin
	   if(rstn == 1'b0) begin 
	       cnu_init_load_en_i <= 1'b0;
	       is_init_load <= 0;
	   end
	   else if(init_load_o == 0 && i > 2 && is_init_load == 0) begin
	       cnu_init_load_en_i <= 1'b0;
	       is_init_load <= 1;
	   end
	   else if(pipe_load_o == 0 && i > 2 && is_init_load == 1) begin
	       is_init_load <= 0;	
	   end
	   else cnu_init_load_en_i <= 1'b1 && ~is_init_load;

	end
	always @(posedge read_clk, negedge rstn) begin
	   if(rstn == 1'b0) cnu_rd_finish_i <= 1'b0;
	   else if(pipe_load_o == 0 && i > 2) cnu_rd_finish_i <= 1'b0;
	   else cnu_rd_finish_i <= 1'b1 && is_init_load;
	end

	initial iter_update_i <= 1'b0;
	logic [4:0] update_cnt; initial update_cnt <= 0;
	always @(posedge write_clk) begin
		if(cnu_wr_o == 1'b1) begin
			if(update_cnt == 31) begin
				iter_update_i <= 1'b0;
			end
			else begin
				update_cnt <= update_cnt + 1;
				iter_update_i <= 1'b1;
			end
		end
		else if(is_init_load == 1) begin
		      update_cnt <= 0;
		end
		else begin 
			iter_update_i <= 1'b0;
		end
	end
	
	initial begin
		##200 $finish;
	end
endmodule

204.33.486/RTL/BSP/DecodingProcessControl/Note/Handshake/cnu_wr_update.vcd
$date
	Tue Oct 27 00:07:58 2020
$end

$version
	Synopsys VCS version N-2017.12-SP2_Full64
$end

$timescale
	1ps
$end

$comment Csum: 1 733d8442176b3b28 $end


$scope module cnu_wr_update_handshake_tb $end
$var reg 1 ! read_clk $end
$var reg 1 " write_clk $end
$var reg 1 # rstn $end
$var reg 1 $ cnu_wr_o $end
$var reg 1 % iter_update_i $end
$var reg 1 & cnu_rd_finish_i $end
$var reg 1 ' init_load_o $end
$var reg 1 ( pipe_load_o $end
$var reg 1 ) cnu_init_load_en_i $end
$var reg 1 * is_init_load $end
$var reg 10 + i [9:0] $end
$var reg 5 , update_cnt [4:0] $end

$scope module handshake_u0 $end
$var wire 1 - cnu_wr_o $end
$var wire 1 . init_load_o $end
$var wire 1 / pipe_load_o $end
$var wire 1 % iter_update_i $end
$var wire 1 & cnu_rd_finish_i $end
$var wire 1 ) cnu_init_load_en_i $end
$var wire 1 ! read_clk $end
$var wire 1 # rstn $end
$var wire 1 % iter_update $end
$var reg 1 0 syncIterUp [1] $end
$var reg 1 1 syncIterUp [0] $end
$var reg 1 2 cnu_rd_finish $end
$var reg 1 3 cnu_init_load_en $end
$var wire 1 4 sig_0 $end
$var wire 1 5 sig_1 $end
$var wire 1 6 sig_2 $end
$var wire 1 7 sig_3 $end
$var wire 1 8 sig_4 $end
$var wire 1 9 sig_5 $end
$var wire 1 : sig_6 $end
$var wire 1 ; sig_7 $end
$var reg 1 < cnu_wr_reg $end
$var reg 2 = wr_trace [1:0] $end
$var reg 1 > init_load_reg $end
$var reg 1 ? pipe_load_reg $end
$upscope $end

$upscope $end

$enddefinitions $end

#0
$dumpvars
03
0)
02
0&
0$
0<
0-
0.
0/
0'
0>
0*
0%
0(
0?
0!
0#
14
05
06
17
08
19
0:
0;
01
00
0"
b0000000000 +
b00000 ,
b00 =
$end
#2000
1"
#4000
0"
#5000
1!
#6000
1"
#8000
0"
#10000
0!
1"
#12000
0"
#14000
1"
#15000
1!
#16000
0"
#18000
1"
#20000
1#
0!
0"
#22000
1"
#24000
0"
#25000
1!
1)
1:
#26000
1"
#28000
0"
#30000
0!
1"
#32000
0"
#34000
1"
#35000
1!
b0000000001 +
13
1>
1.
1'
15
16
18
07
#36000
0"
#38000
1"
#40000
0!
0"
#42000
1"
#44000
0"
#45000
1!
b0000000010 +
1<
1$
08
1-
17
04
19
06
07
09
0:
#46000
1"
b00001 ,
1%
14
16
17
19
1:
#48000
0"
#50000
0!
1"
b01 =
b00010 ,
#52000
0"
#54000
1"
b00011 ,
#55000
1!
b0000000011 +
11
#56000
0"
#58000
1"
b00100 ,
#60000
0!
0"
b11 =
#62000
1"
b00101 ,
#64000
0"
#65000
1!
b0000000000 +
10
#66000
1"
b00110 ,
#68000
0"
#70000
0!
1"
b00111 ,
#72000
0"
#74000
1"
b01000 ,
#75000
1!
b0000000001 +
#76000
0"
#78000
1"
b01001 ,
#80000
0!
0"
#82000
1"
b01010 ,
#84000
0"
#85000
1!
b0000000010 +
#86000
1"
b01011 ,
#88000
0"
#90000
0!
1"
b01100 ,
#92000
0"
#94000
1"
b01101 ,
#95000
1!
b0000000011 +
#96000
0"
#98000
1"
b01110 ,
#100000
0!
0"
#102000
1"
b01111 ,
#104000
0"
#105000
1!
b0000000000 +
#106000
1"
b10000 ,
#108000
0"
#110000
0!
1"
b10001 ,
#112000
0"
#114000
1"
b10010 ,
#115000
1!
b0000000001 +
#116000
0"
#118000
1"
b10011 ,
#120000
0!
0"
#122000
1"
b10100 ,
#124000
0"
#125000
1!
b0000000010 +
#126000
1"
b10101 ,
#128000
0"
#130000
0!
1"
b10110 ,
#132000
0"
#134000
1"
b10111 ,
#135000
1!
b0000000011 +
#136000
0"
#138000
1"
b11000 ,
#140000
0!
0"
#142000
1"
b11001 ,
#144000
0"
#145000
1!
b0000000000 +
#146000
1"
b11010 ,
#148000
0"
#150000
0!
1"
b11011 ,
#152000
0"
#154000
1"
b11100 ,
#155000
1!
b0000000001 +
#156000
0"
#158000
1"
b11101 ,
#160000
0!
0"
#162000
1"
b11110 ,
#164000
0"
#165000
1!
b0000000010 +
#166000
1"
b11111 ,
#168000
0"
#170000
0!
1"
0%
04
06
07
09
0:
#172000
0"
#174000
1"
#175000
1!
b0000000011 +
01
0<
0$
0-
17
14
0>
0.
0'
05
19
1:
06
#176000
0"
#178000
1"
#180000
0!
0"
b10 =
#182000
1"
#184000
0"
#185000
1!
b0000000000 +
0)
0:
1*
00
#186000
1"
b00000 ,
#188000
0"
#190000
0!
1"
b00 =
#192000
0"
#194000
1"
#195000
1!
1&
1;
03
#196000
0"
#198000
1"
#200000
0!
0"
#202000
1"
#204000
0"
#205000
1!
b0000000001 +
12
1?
1/
1(
15
16
18
07
#206000
1"
#208000
0"
#210000
0!
1"
#212000
0"
#214000
1"
#215000
1!
b0000000010 +
1<
1$
08
1-
17
04
19
06
07
09
0;
#216000
0"
#218000
1"
b00001 ,
1%
14
16
17
19
1;
#220000
0!
0"
b01 =
#222000
1"
b00010 ,
#224000
0"
#225000
1!
b0000000011 +
11
#226000
1"
b00011 ,
#228000
0"
#230000
0!
1"
b11 =
b00100 ,
#232000
0"
#234000
1"
b00101 ,
#235000
1!
b0000000000 +
10
#236000
0"
#238000
1"
b00110 ,
#240000
0!
0"
#242000
1"
b00111 ,
#244000
0"
#245000
1!
b0000000001 +
#246000
1"
b01000 ,
#248000
0"
#250000
0!
1"
b01001 ,
#252000
0"
#254000
1"
b01010 ,
#255000
1!
b0000000010 +
#256000
0"
#258000
1"
b01011 ,
#260000
0!
0"
#262000
1"
b01100 ,
#264000
0"
#265000
1!
b0000000011 +
#266000
1"
b01101 ,
#268000
0"
#270000
0!
1"
b01110 ,
#272000
0"
#274000
1"
b01111 ,
#275000
1!
b0000000000 +
#276000
0"
#278000
1"
b10000 ,
#280000
0!
0"
#282000
1"
b10001 ,
#284000
0"
#285000
1!
b0000000001 +
#286000
1"
b10010 ,
#288000
0"
#290000
0!
1"
b10011 ,
#292000
0"
#294000
1"
b10100 ,
#295000
1!
b0000000010 +
#296000
0"
#298000
1"
b10101 ,
#300000
0!
0"
#302000
1"
b10110 ,
#304000
0"
#305000
1!
b0000000011 +
#306000
1"
b10111 ,
#308000
0"
#310000
0!
1"
b11000 ,
#312000
0"
#314000
1"
b11001 ,
#315000
1!
b0000000000 +
#316000
0"
#318000
1"
b11010 ,
#320000
0!
0"
#322000
1"
b11011 ,
#324000
0"
#325000
1!
b0000000001 +
#326000
1"
b11100 ,
#328000
0"
#330000
0!
1"
b11101 ,
#332000
0"
#334000
1"
b11110 ,
#335000
1!
b0000000010 +
#336000
0"
#338000
1"
b11111 ,
#340000
0!
0"
#342000
1"
0%
04
06
07
09
0;
#344000
0"
#345000
1!
b0000000011 +
01
0<
0$
0-
17
14
0?
0/
0(
05
19
1;
06
#346000
1"
b00000 ,
#348000
0"
#350000
0!
1"
b10 =
#352000
0"
#354000
1"
#355000
1!
b0000000000 +
0*
0&
0;
00
#356000
0"
#358000
1"
#360000
0!
0"
b00 =
#362000
1"
#364000
0"
#365000
1!
1)
1:
02
#366000
1"
#368000
0"
#370000
0!
1"
#372000
0"
#374000
1"
#375000
1!
b0000000001 +
13
1>
1.
1'
15
16
18
07
#376000
0"
#378000
1"
#380000
0!
0"
#382000
1"
#384000
0"
#385000
1!
b0000000010 +
1<
1$
08
1-
17
04
19
06
07
09
0:
#386000
1"
b00001 ,
1%
14
16
17
19
1:
#388000
0"
#390000
0!
1"
b01 =
b00010 ,
#392000
0"
#394000
1"
b00011 ,
#395000
1!
b0000000011 +
11
#396000
0"
#398000
1"
b00100 ,
#400000
0!
0"
b11 =
#402000
1"
b00101 ,
#404000
0"
#405000
1!
b0000000000 +
10
#406000
1"
b00110 ,
#408000
0"
#410000
0!
1"
b00111 ,
#412000
0"
#414000
1"
b01000 ,
#415000
1!
b0000000001 +
#416000
0"
#418000
1"
b01001 ,
#420000
0!
0"
#422000
1"
b01010 ,
#424000
0"
#425000
1!
b0000000010 +
#426000
1"
b01011 ,
#428000
0"
#430000
0!
1"
b01100 ,
#432000
0"
#434000
1"
b01101 ,
#435000
1!
b0000000011 +
#436000
0"
#438000
1"
b01110 ,
#440000
0!
0"
#442000
1"
b01111 ,
#444000
0"
#445000
1!
b0000000000 +
#446000
1"
b10000 ,
#448000
0"
#450000
0!
1"
b10001 ,
#452000
0"
#454000
1"
b10010 ,
#455000
1!
b0000000001 +
#456000
0"
#458000
1"
b10011 ,
#460000
0!
0"
#462000
1"
b10100 ,
#464000
0"
#465000
1!
b0000000010 +
#466000
1"
b10101 ,
#468000
0"
#470000
0!
1"
b10110 ,
#472000
0"
#474000
1"
b10111 ,
#475000
1!
b0000000011 +
#476000
0"
#478000
1"
b11000 ,
#480000
0!
0"
#482000
1"
b11001 ,
#484000
0"
#485000
1!
b0000000000 +
#486000
1"
b11010 ,
#488000
0"
#490000
0!
1"
b11011 ,
#492000
0"
#494000
1"
b11100 ,
#495000
1!
b0000000001 +
#496000
0"
#498000
1"
b11101 ,
#500000
0!
0"
#502000
1"
b11110 ,
#504000
0"
#505000
1!
b0000000010 +
#506000
1"
b11111 ,
#508000
0"
#510000
0!
1"
0%
04
06
07
09
0:
#512000
0"
#514000
1"
#515000
1!
b0000000011 +
01
0<
0$
0-
17
14
0>
0.
0'
05
19
1:
06
#516000
0"
#518000
1"
#520000
0!
0"
b10 =
#522000
1"
#524000
0"
#525000
1!
b0000000000 +
0)
0:
1*
00
#526000
1"
b00000 ,
#528000
0"
#530000
0!
1"
b00 =
#532000
0"
#534000
1"
#535000
1!
1&
1;
03
#536000
0"
#538000
1"
#540000
0!
0"
#542000
1"
#544000
0"
#545000
1!
b0000000001 +
12
1?
1/
1(
15
16
18
07
#546000
1"
#548000
0"
#550000
0!
1"
#552000
0"
#554000
1"
#555000
1!
b0000000010 +
1<
1$
08
1-
17
04
19
06
07
09
0;
#556000
0"
#558000
1"
b00001 ,
1%
14
16
17
19
1;
#560000
0!
0"
b01 =
#562000
1"
b00010 ,
#564000
0"
#565000
1!
b0000000011 +
11
#566000
1"
b00011 ,
#568000
0"
#570000
0!
1"
b11 =
b00100 ,
#572000
0"
#574000
1"
b00101 ,
#575000
1!
b0000000000 +
10
#576000
0"
#578000
1"
b00110 ,
#580000
0!
0"
#582000
1"
b00111 ,
#584000
0"
#585000
1!
b0000000001 +
#586000
1"
b01000 ,
#588000
0"
#590000
0!
1"
b01001 ,
#592000
0"
#594000
1"
b01010 ,
#595000
1!
b0000000010 +
#596000
0"
#598000
1"
b01011 ,
#600000
0!
0"
#602000
1"
b01100 ,
#604000
0"
#605000
1!
b0000000011 +
#606000
1"
b01101 ,
#608000
0"
#610000
0!
1"
b01110 ,
#612000
0"
#614000
1"
b01111 ,
#615000
1!
b0000000000 +
#616000
0"
#618000
1"
b10000 ,
#620000
0!
0"
#622000
1"
b10001 ,
#624000
0"
#625000
1!
b0000000001 +
#626000
1"
b10010 ,
#628000
0"
#630000
0!
1"
b10011 ,
#632000
0"
#634000
1"
b10100 ,
#635000
1!
b0000000010 +
#636000
0"
#638000
1"
b10101 ,
#640000
0!
0"
#642000
1"
b10110 ,
#644000
0"
#645000
1!
b0000000011 +
#646000
1"
b10111 ,
#648000
0"
#650000
0!
1"
b11000 ,
#652000
0"
#654000
1"
b11001 ,
#655000
1!
b0000000000 +
#656000
0"
#658000
1"
b11010 ,
#660000
0!
0"
#662000
1"
b11011 ,
#664000
0"
#665000
1!
b0000000001 +
#666000
1"
b11100 ,
#668000
0"
#670000
0!
1"
b11101 ,
#672000
0"
#674000
1"
b11110 ,
#675000
1!
b0000000010 +
#676000
0"
#678000
1"
b11111 ,
#680000
0!
0"
#682000
1"
0%
04
06
07
09
0;
#684000
0"
#685000
1!
b0000000011 +
01
0<
0$
0-
17
14
0?
0/
0(
05
19
1;
06
#686000
1"
b00000 ,
#688000
0"
#690000
0!
1"
b10 =
#692000
0"
#694000
1"
#695000
1!
b0000000000 +
0*
0&
0;
00
#696000
0"
#698000
1"
#700000
0!
0"
b00 =
#702000
1"
#704000
0"
#705000
1!
1)
1:
02
#706000
1"
#708000
0"
#710000
0!
1"
#712000
0"
#714000
1"
#715000
1!
b0000000001 +
13
1>
1.
1'
15
16
18
07
#716000
0"
#718000
1"
#720000
0!
0"
#722000
1"
#724000
0"
#725000
1!
b0000000010 +
1<
1$
08
1-
17
04
19
06
07
09
0:
#726000
1"
b00001 ,
1%
14
16
17
19
1:
#728000
0"
#730000
0!
1"
b01 =
b00010 ,
#732000
0"
#734000
1"
b00011 ,
#735000
1!
b0000000011 +
11
#736000
0"
#738000
1"
b00100 ,
#740000
0!
0"
b11 =
#742000
1"
b00101 ,
#744000
0"
#745000
1!
b0000000000 +
10
#746000
1"
b00110 ,
#748000
0"
#750000
0!
1"
b00111 ,
#752000
0"
#754000
1"
b01000 ,
#755000
1!
b0000000001 +
#756000
0"
#758000
1"
b01001 ,
#760000
0!
0"
#762000
1"
b01010 ,
#764000
0"
#765000
1!
b0000000010 +
#766000
1"
b01011 ,
#768000
0"
#770000
0!
1"
b01100 ,
#772000
0"
#774000
1"
b01101 ,
#775000
1!
b0000000011 +
#776000
0"
#778000
1"
b01110 ,
#780000
0!
0"
#782000
1"
b01111 ,
#784000
0"
#785000
1!
b0000000000 +
#786000
1"
b10000 ,
#788000
0"
#790000
0!
1"
b10001 ,
#792000
0"
#794000
1"
b10010 ,
#795000
1!
b0000000001 +
#796000
0"
#798000
1"
b10011 ,
